{
    "type": "FeatureCollection",
    "features": [
        {
            "type": "Feature",
            "geometry": {
              "type": "Point",
              "coordinates": [-71.413610, 41.820120]
            },
            "properties": {
              "name": "Beneficent Congregational Church"
            }
          }
    ]}